sneak/Http.py
sneak/Netool.py
sneak/Tor.py
sneak/__init__.py
sneak/test.py
sneak/test_data/__init__.py
sneak/test_data/test_settings.py
sneak-0.1.3.dist-info/DESCRIPTION.rst
sneak-0.1.3.dist-info/METADATA
sneak-0.1.3.dist-info/RECORD
sneak-0.1.3.dist-info/WHEEL
sneak-0.1.3.dist-info/metadata.json
sneak-0.1.3.dist-info/top_level.txt
