Metadata-Version: 2.0
Name: sneak
Version: 0.1.3
Summary: Sneak is a URL transfer tool based on Tor technology.
Home-page: https://github.com/yudazilian/Sneak
Author: yd
Author-email: davisfreeman1015@gmail.com
License: Apache 2.0
Keywords: curl tor http
Platform: UNKNOWN
Requires-Dist: stem
Requires-Dist: pycurl
